document_extraction_module/__init__.py
document_extraction_module/_version.py
document_extraction_module/config.py
document_extraction_module/constants.py
document_extraction_module/extraction.py
document_extraction_module/extraction_class_type.py
document_extraction_module/file_process.py
document_extraction_module/landing_ai_parse.py
document_extraction_module/prompt_processing.py
document_extraction_module-0.1.1.dist-info/METADATA
document_extraction_module-0.1.1.dist-info/WHEEL
document_extraction_module-0.1.1.dist-info/entry_points.txt
document_extraction_module-0.1.1.dist-info/RECORD
