Metadata-Version: 2.4
Name: document-extraction-module
Version: 0.1.1
Summary: Extraction / Parse of any PDF document within minutes
Author-email: Optimo Capital <muraribv22@gmail.com>
License: MIT
Requires-Python: >=3.10
Requires-Dist: agentic-doc
Requires-Dist: aiohttp
Requires-Dist: aiolimiter
Requires-Dist: asyncio
Requires-Dist: dspy
Requires-Dist: fastapi
Requires-Dist: numpy
Requires-Dist: openai
Requires-Dist: pandas
Requires-Dist: pdf2image
Requires-Dist: pillow
Requires-Dist: pydantic
Requires-Dist: pymupdf
Requires-Dist: pyrfc3339
Requires-Dist: requests
Requires-Dist: tiktoken
Requires-Dist: tokenizers
Requires-Dist: tqdm
Requires-Dist: wheel
